pararamio/__init__.py
pararamio/client.py
pararamio/cookie_manager.py
pararamio/exceptions.py
pararamio/py.typed
pararamio/schemas.py
pararamio/types.py
pararamio/_core/__init__.py
pararamio/_core/_types.py
pararamio/_core/client_protocol.py
pararamio/_core/cookie_manager.py
pararamio/_core/endpoints.py
pararamio/_core/py.typed
pararamio/_core/validators.py
pararamio/_core/api_schemas/__init__.py
pararamio/_core/api_schemas/requests/__init__.py
pararamio/_core/api_schemas/requests/chat.py
pararamio/_core/api_schemas/requests/deferred_post.py
pararamio/_core/api_schemas/requests/group.py
pararamio/_core/api_schemas/requests/post.py
pararamio/_core/api_schemas/responses/__init__.py
pararamio/_core/api_schemas/responses/activity.py
pararamio/_core/api_schemas/responses/attachment.py
pararamio/_core/api_schemas/responses/base.py
pararamio/_core/api_schemas/responses/bot.py
pararamio/_core/api_schemas/responses/chat.py
pararamio/_core/api_schemas/responses/common.py
pararamio/_core/api_schemas/responses/deferred_post.py
pararamio/_core/api_schemas/responses/deferred_post_create.py
pararamio/_core/api_schemas/responses/events.py
pararamio/_core/api_schemas/responses/file.py
pararamio/_core/api_schemas/responses/group.py
pararamio/_core/api_schemas/responses/message.py
pararamio/_core/api_schemas/responses/poll.py
pararamio/_core/api_schemas/responses/post.py
pararamio/_core/api_schemas/responses/read_status.py
pararamio/_core/api_schemas/responses/rerere.py
pararamio/_core/api_schemas/responses/team.py
pararamio/_core/api_schemas/responses/user.py
pararamio/_core/constants/__init__.py
pararamio/_core/constants/base.py
pararamio/_core/constants/endpoints.py
pararamio/_core/exceptions/__init__.py
pararamio/_core/exceptions/auth.py
pararamio/_core/exceptions/base.py
pararamio/_core/models/__init__.py
pararamio/_core/models/activity.py
pararamio/_core/models/attachment.py
pararamio/_core/models/base.py
pararamio/_core/models/bot.py
pararamio/_core/models/chat.py
pararamio-3.0.10.dist-info/METADATA
pararamio-3.0.10.dist-info/WHEEL
pararamio-3.0.10.dist-info/top_level.txt
pararamio-3.0.10.dist-info/RECORD
